{
  "id": {
    "address": "texas_poker",
    "name": "reveal_token_proof"
  },
  "doc": null,
  "immediate_dependencies": [
    {
      "address": "sui",
      "name": "bls12381"
    },
    {
      "address": "sui",
      "name": "group_ops"
    },
    {
      "address": "texas_poker",
      "name": "bls_elgamal"
    },
    {
      "address": "texas_poker",
      "name": "bls_scalar"
    },
    {
      "address": "texas_poker",
      "name": "bls_transcript"
    }
  ],
  "attributes": [],
  "functions": {
    "user_public_key": {
      "source_index": 0,
      "index": 0,
      "doc": null,
      "attributes": [],
      "visibility": "Public",
      "entry": false,
      "type_parameters": [],
      "parameters": [
        {
          "name": "proof",
          "type_": {
            "Reference": [
              false,
              {
                "Datatype": {
                  "module": {
                    "address": "texas_poker",
                    "name": "reveal_token_proof"
                  },
                  "name": "RevealTokenProof",
                  "type_arguments": []
                }
              }
            ]
          }
        }
      ],
      "return_": [
        {
          "Reference": [
            false,
            {
              "vector": "u8"
            }
          ]
        }
      ]
    },
    "commitment_t1": {
      "source_index": 1,
      "index": 1,
      "doc": null,
      "attributes": [],
      "visibility": "Public",
      "entry": false,
      "type_parameters": [],
      "parameters": [
        {
          "name": "proof",
          "type_": {
            "Reference": [
              false,
              {
                "Datatype": {
                  "module": {
                    "address": "texas_poker",
                    "name": "reveal_token_proof"
                  },
                  "name": "RevealTokenProof",
                  "type_arguments": []
                }
              }
            ]
          }
        }
      ],
      "return_": [
        {
          "Reference": [
            false,
            {
              "vector": "u8"
            }
          ]
        }
      ]
    },
    "commitment_t2": {
      "source_index": 2,
      "index": 2,
      "doc": null,
      "attributes": [],
      "visibility": "Public",
      "entry": false,
      "type_parameters": [],
      "parameters": [
        {
          "name": "proof",
          "type_": {
            "Reference": [
              false,
              {
                "Datatype": {
                  "module": {
                    "address": "texas_poker",
                    "name": "reveal_token_proof"
                  },
                  "name": "RevealTokenProof",
                  "type_arguments": []
                }
              }
            ]
          }
        }
      ],
      "return_": [
        {
          "Reference": [
            false,
            {
              "vector": "u8"
            }
          ]
        }
      ]
    },
    "response_s": {
      "source_index": 3,
      "index": 3,
      "doc": null,
      "attributes": [],
      "visibility": "Public",
      "entry": false,
      "type_parameters": [],
      "parameters": [
        {
          "name": "proof",
          "type_": {
            "Reference": [
              false,
              {
                "Datatype": {
                  "module": {
                    "address": "texas_poker",
                    "name": "reveal_token_proof"
                  },
                  "name": "RevealTokenProof",
                  "type_arguments": []
                }
              }
            ]
          }
        }
      ],
      "return_": [
        {
          "Reference": [
            false,
            {
              "vector": "u8"
            }
          ]
        }
      ]
    },
    "new": {
      "source_index": 4,
      "index": 4,
      "doc": null,
      "attributes": [],
      "visibility": "Public",
      "entry": false,
      "type_parameters": [],
      "parameters": [
        {
          "name": "user_public_key",
          "type_": {
            "vector": "u8"
          }
        },
        {
          "name": "commitment_t1",
          "type_": {
            "vector": "u8"
          }
        },
        {
          "name": "commitment_t2",
          "type_": {
            "vector": "u8"
          }
        },
        {
          "name": "response_s",
          "type_": {
            "vector": "u8"
          }
        }
      ],
      "return_": [
        {
          "Datatype": {
            "module": {
              "address": "texas_poker",
              "name": "reveal_token_proof"
            },
            "name": "RevealTokenProof",
            "type_arguments": []
          }
        }
      ]
    },
    "verify": {
      "source_index": 5,
      "index": 5,
      "doc": " 验证 RevealTokenProof\n 证明 log_G(pk) == log_c1(reveal_token)，即两者离散对数相同",
      "attributes": [],
      "visibility": "Public",
      "entry": false,
      "type_parameters": [],
      "parameters": [
        {
          "name": "proof",
          "type_": {
            "Reference": [
              false,
              {
                "Datatype": {
                  "module": {
                    "address": "texas_poker",
                    "name": "reveal_token_proof"
                  },
                  "name": "RevealTokenProof",
                  "type_arguments": []
                }
              }
            ]
          }
        },
        {
          "name": "encrypted_card",
          "type_": {
            "Reference": [
              false,
              {
                "Datatype": {
                  "module": {
                    "address": "texas_poker",
                    "name": "bls_elgamal"
                  },
                  "name": "ElGamalCiphertext",
                  "type_arguments": []
                }
              }
            ]
          }
        },
        {
          "name": "reveal_token",
          "type_": {
            "Reference": [
              false,
              {
                "Datatype": {
                  "module": {
                    "address": "sui",
                    "name": "group_ops"
                  },
                  "name": "Element",
                  "type_arguments": [
                    {
                      "phantom": true,
                      "argument": {
                        "Datatype": {
                          "module": {
                            "address": "sui",
                            "name": "bls12381"
                          },
                          "name": "G1",
                          "type_arguments": []
                        }
                      }
                    }
                  ]
                }
              }
            ]
          }
        },
        {
          "name": "expected_pk",
          "type_": {
            "Reference": [
              false,
              {
                "Datatype": {
                  "module": {
                    "address": "sui",
                    "name": "group_ops"
                  },
                  "name": "Element",
                  "type_arguments": [
                    {
                      "phantom": true,
                      "argument": {
                        "Datatype": {
                          "module": {
                            "address": "sui",
                            "name": "bls12381"
                          },
                          "name": "G1",
                          "type_arguments": []
                        }
                      }
                    }
                  ]
                }
              }
            ]
          }
        }
      ],
      "return_": [
        "bool"
      ]
    }
  },
  "structs": {
    "RevealTokenProof": {
      "index": 0,
      "doc": " Chaum-Pedersen DLEq 证明：log_G(pk) == log_c1(reveal_token) == sk\n 证明持有者知道 sk 使得 pk = G * sk 且 reveal_token = c1 * sk",
      "attributes": [],
      "abilities": [
        "Copy",
        "Drop",
        "Store"
      ],
      "type_parameters": [],
      "fields": {
        "positional_fields": false,
        "fields": {
          "user_public_key": {
            "index": 0,
            "doc": null,
            "type_": {
              "vector": "u8"
            }
          },
          "commitment_t1": {
            "index": 1,
            "doc": null,
            "type_": {
              "vector": "u8"
            }
          },
          "commitment_t2": {
            "index": 2,
            "doc": null,
            "type_": {
              "vector": "u8"
            }
          },
          "response_s": {
            "index": 3,
            "doc": null,
            "type_": {
              "vector": "u8"
            }
          }
        }
      }
    }
  },
  "enums": {}
}